chained_accounts/__init__.py
chained_accounts/base.py
chained_accounts/cli.py
chained_accounts/exceptions.py
chained_accounts-0.0.1.dist-info/LICENSE
chained_accounts-0.0.1.dist-info/METADATA
chained_accounts-0.0.1.dist-info/WHEEL
chained_accounts-0.0.1.dist-info/entry_points.txt
chained_accounts-0.0.1.dist-info/top_level.txt
chained_accounts-0.0.1.dist-info/RECORD
