Metadata-Version: 2.1
Name: chained-accounts
Version: 0.0.1
Summary: A thin framework to help applications and users manage multiple ethereum accounts on multiple chains.
Home-page: https://github.com/pydefi/chained_accounts
Author: PyDefi Development Team
Author-email: clamdad+pydefi@protonmail.com
License: MIT
Keywords: ethereum,keystore,key management,private keys,cross-chain,multi-chain
Platform: Linux
Platform: Windows
Platform: Mac
Classifier: Development Status :: 3 - Alpha
Classifier: Intended Audience :: Developers
Classifier: Topic :: Office/Business :: Financial
Classifier: License :: OSI Approved :: MIT License
Classifier: Programming Language :: Python :: 3.8
Classifier: Programming Language :: Python :: 3.9
Requires-Python: >=3.8
License-File: LICENSE
Requires-Dist: click
Requires-Dist: eth-account
